metathreads/__init__.py
metathreads/config.py
metathreads/constants.py
metathreads/metathreads.py
metathreads/request_util.py
metathreads/util.py
metathreads-0.0.4.dist-info/LICENSE
metathreads-0.0.4.dist-info/METADATA
metathreads-0.0.4.dist-info/WHEEL
metathreads-0.0.4.dist-info/top_level.txt
metathreads-0.0.4.dist-info/RECORD
