Metadata-Version: 2.1
Name: metathreads
Version: 0.0.4
Summary: MetaThreads is Meta Threads-API to interact with Instagram threads app, extract data and perform actions. The library is written in python. MetaThreads API lets you fetch user's threads, thread replies, user's data, user's friends. Actions like posting a thread, like/unlike threads etc. can easily be perfomed with the api.
Home-page: https://github.com/iSarabjitDhiman/MetaThreads
Author: Sarabjit Dhiman
Author-email: hello@sarabjitdhiman.com
License: MIT
Keywords: metathreads,threads-api,threadsapi,meta threads api,threads api,instagram threads,threads-api-python,insta-threads
Classifier: Development Status :: 3 - Alpha
Classifier: Intended Audience :: End Users/Desktop
Classifier: Intended Audience :: Developers
Classifier: Operating System :: Microsoft :: Windows
Classifier: Operating System :: MacOS :: MacOS X
Classifier: Operating System :: Unix
Classifier: License :: OSI Approved :: MIT License
Classifier: Topic :: Software Development :: Build Tools
Classifier: Programming Language :: Python :: 3
Requires-Python: >=3
License-File: LICENSE
Requires-Dist: anyio (==3.7.1)
Requires-Dist: beautifulsoup4 (==4.12.2)
Requires-Dist: bs4 (==0.0.1)
Requires-Dist: certifi (==2023.5.7)
Requires-Dist: exceptiongroup (==1.1.2)
Requires-Dist: h11 (==0.14.0)
Requires-Dist: httpcore (==0.17.3)
Requires-Dist: httpx (==0.24.1)
Requires-Dist: idna (==3.4)
Requires-Dist: lxml (==4.9.3)
Requires-Dist: sniffio (==1.3.0)
Requires-Dist: soupsieve (==2.4.1)
